zh_rasa/__init__.py
zh_rasa/version.txt
zh_rasa/classifiers/__init__.py
zh_rasa/classifiers/tfnlu_classifier.py
zh_rasa/extractors/__init__.py
zh_rasa/extractors/tfnlu_extractor.py
zh_rasa/tokenizers/__init__.py
zh_rasa/tokenizers/bert_tokenizer.py
zh_rasa/tokenizers/test.py
zh_rasa/tokenizers/vocab.txt
zh_rasa-0.0.11.dist-info/LICENSE
zh_rasa-0.0.11.dist-info/METADATA
zh_rasa-0.0.11.dist-info/WHEEL
zh_rasa-0.0.11.dist-info/top_level.txt
zh_rasa-0.0.11.dist-info/RECORD
